fintoc/__init__.py
fintoc/client.py
fintoc/constants.py
fintoc/core.py
fintoc/errors.py
fintoc/jws.py
fintoc/managers/__init__.py
fintoc/managers/accounts_manager.py
fintoc/managers/charges_manager.py
fintoc/managers/checkout_sessions_manager.py
fintoc/managers/invoices_manager.py
fintoc/managers/links_manager.py
fintoc/managers/movements_manager.py
fintoc/managers/payment_intents_manager.py
fintoc/managers/payment_links_manager.py
fintoc/managers/refresh_intents_manager.py
fintoc/managers/refunds_manager.py
fintoc/managers/subscription_intents_manager.py
fintoc/managers/subscriptions_manager.py
fintoc/managers/tax_returns_manager.py
fintoc/managers/v2/__init__.py
fintoc/managers/v2/account_numbers_manager.py
fintoc/managers/v2/account_verifications_manager.py
fintoc/managers/v2/accounts_manager.py
fintoc/managers/v2/customers_manager.py
fintoc/managers/v2/entities_manager.py
fintoc/managers/v2/movements_manager.py
fintoc/managers/v2/simulate_manager.py
fintoc/managers/v2/transfers_manager.py
fintoc/managers/webhook_endpoints_manager.py
fintoc/mixins/__init__.py
fintoc/mixins/manager_mixin.py
fintoc/mixins/resource_mixin.py
fintoc/paginator.py
fintoc/resource_handlers.py
fintoc/resources/__init__.py
fintoc/resources/account.py
fintoc/resources/balance.py
fintoc/resources/charge.py
fintoc/resources/checkout_session.py
fintoc/resources/generic_fintoc_resource.py
fintoc/resources/income.py
fintoc/resources/institution.py
fintoc/resources/institution_invoice.py
fintoc/resources/institution_tax_return.py
fintoc/resources/invoice.py
fintoc/resources/link.py
fintoc/resources/movement.py
fintoc/resources/other_taxes.py
fintoc/resources/payment_intent.py
fintoc/resources/payment_link.py
fintoc/resources/refresh_intent.py
fintoc/resources/refund.py
fintoc/resources/services_invoice.py
fintoc/resources/subscription.py
fintoc/resources/subscription_intent.py
fintoc/resources/tax_return.py
fintoc/resources/taxpayer.py
fintoc/resources/tobacco_taxes.py
fintoc-2.15.0.dist-info/LICENSE.md
fintoc-2.15.0.dist-info/METADATA
fintoc-2.15.0.dist-info/WHEEL
fintoc-2.15.0.dist-info/RECORD
