Metadata-Version: 2.3
Name: fintoc
Version: 2.15.0
Summary: The official Python client for the Fintoc API.
License: BSD-3-Clause
Author: Daniel Leal
Author-email: daniel@fintoc.com
Maintainer: Daniel Leal
Maintainer-email: daniel@fintoc.com
Requires-Python: >=3.7,<4.0
Classifier: License :: OSI Approved :: BSD License
Classifier: Programming Language :: Python :: 3
Classifier: Programming Language :: Python :: 3.7
Classifier: Programming Language :: Python :: 3.8
Classifier: Programming Language :: Python :: 3.9
Classifier: Programming Language :: Python :: 3.10
Classifier: Programming Language :: Python :: 3.11
Classifier: Programming Language :: Python :: 3.12
Classifier: Programming Language :: Python :: 3.13
Requires-Dist: cryptography (<44.0.0)
Requires-Dist: httpx (>=0.16,<1.0)
Project-URL: Homepage, https://fintoc.com/
Project-URL: Issue Tracker, https://github.com/fintoc-com/fintoc-python/issues
Project-URL: Repository, https://github.com/fintoc-com/fintoc-python
